{
  "project_info": {
    "project_number": "647323645231",
    "project_id": "pickmecustomer01",
    "storage_bucket": "pickmecustomer01.appspot.com"
  },
  "client": [
    {
      "client_info": {
        "mobilesdk_app_id": "1:647323645231:android:9833db008c732b3bdcddda",
        "android_client_info": {
          "package_name": "com.dragongroup.pickmecustomer01"
        }
      },
      "oauth_client": [
        {
          "client_id": "647323645231-e9akboungsa8vs430h71ptcgigc0mlkv.apps.googleusercontent.com",
          "client_type": 3
        }
      ],
      "api_key": [
        {
          "current_key": "AIzaSyAtM_KHG2oujrIpjh8TNtlyUvSiEG1n-l8"
        }
      ],
      "services": {
        "appinvite_service": {
          "other_platform_oauth_client": [
            {
              "client_id": "647323645231-e9akboungsa8vs430h71ptcgigc0mlkv.apps.googleusercontent.com",
              "client_type": 3
            }
          ]
        }
      }
    }
  ],
  "configuration_version": "1"
}